setup.py
eoinoms_distributions/Binomialdistribution.py
eoinoms_distributions/Gaussiandistribution.py
eoinoms_distributions/Generaldistribution.py
eoinoms_distributions/__init__.py
eoinoms_distributions.egg-info/PKG-INFO
eoinoms_distributions.egg-info/SOURCES.txt
eoinoms_distributions.egg-info/dependency_links.txt
eoinoms_distributions.egg-info/not-zip-safe
eoinoms_distributions.egg-info/top_level.txt