Metadata-Version: 1.0
Name: eoinoms-distributions
Version: 0.2
Summary: Gaussian and Binomial distributions
Home-page: UNKNOWN
Author: Eoin O'Malley
Author-email: eoinom@gmail.com
License: UNKNOWN
Platform: UNKNOWN
